<annotation>
	<folder>collected</folder>
	<filename>thanks.6b3c00ec-d4d7-11ed-9c90-4cd577e27178.jpg</filename>
	<path>C:\RealTimeObjectDetection\Tensorflow\workspace\images\collected\thanks.6b3c00ec-d4d7-11ed-9c90-4cd577e27178.jpg</path>
	<source>
		<database>Unknown</database>
	</source>
	<size>
		<width>640</width>
		<height>480</height>
		<depth>3</depth>
	</size>
	<segmented>0</segmented>
	<object>
		<name>Thank You</name>
		<pose>Unspecified</pose>
		<truncated>0</truncated>
		<difficult>0</difficult>
		<bndbox>
			<xmin>108</xmin>
			<ymin>274</ymin>
			<xmax>487</xmax>
			<ymax>440</ymax>
		</bndbox>
	</object>
</annotation>
